pysemigroup/__init__.py
pysemigroup/automata.py
pysemigroup/generate.py
pysemigroup/learning.py
pysemigroup/logic.py
pysemigroup/regular_language.py
pysemigroup/ring.py
pysemigroup/transition_semigroup.py
pysemigroup/utils.py
pysemigroup-0.3a8.dist-info/LICENSE
pysemigroup-0.3a8.dist-info/METADATA
pysemigroup-0.3a8.dist-info/WHEEL
pysemigroup-0.3a8.dist-info/top_level.txt
pysemigroup-0.3a8.dist-info/RECORD
