Metadata-Version: 2.1
Name: pysemigroup
Version: 0.3a8
Summary: A tool to manipulate transitions semigroups and display them
Home-page: https://gitlab.inria.fr/cpaperma/pysemigroup
Author: Charles Paperman
Author-email: charles.paperman@univ-lille.fr
License: GPLv2+
Keywords: automata semigroups monoid regular language
Platform: UNKNOWN
Requires-Dist: networkx
Requires-Dist: numpy
